{"version":1,"resource":"vscode-remote://ssh-remote%2B7b22686f73744e616d65223a2257656174686572417069416972666c6f77227d/home/ubuntu/airflow/dags/weather_dag.py","entries":[{"id":"IbQy.py","timestamp":1692153856722},{"id":"dHpn.py","timestamp":1692153871846},{"id":"jVY3.py","timestamp":1692153899798},{"id":"D9rg.py","timestamp":1692153957340},{"id":"uZYj.py","timestamp":1692153981096},{"id":"qqo3.py","timestamp":1692154009171},{"id":"9BLw.py","timestamp":1692154023639},{"id":"HkSa.py","timestamp":1692154094533},{"id":"kUT7.py","timestamp":1692154122789},{"id":"ZrK9.py","timestamp":1692154157460},{"id":"V1c7.py","timestamp":1692154221707},{"id":"ifau.py","timestamp":1692154231735},{"id":"vRn9.py","timestamp":1692154263950},{"id":"402i.py","timestamp":1692154277234},{"id":"mRJs.py","timestamp":1692154455614},{"id":"rwGr.py","timestamp":1692154521805},{"id":"Eatm.py","timestamp":1692154660402},{"id":"Jfku.py","source":"undoRedo.source","timestamp":1692154661626},{"id":"2FdT.py","timestamp":1692154692073},{"id":"m6qi.py","timestamp":1692154706981},{"id":"15P0.py","source":"undoRedo.source","timestamp":1692154716672},{"id":"v1co.py","timestamp":1692154722660},{"id":"SckB.py","timestamp":1692155151215},{"id":"XzuG.py","timestamp":1692155184715},{"id":"zUAi.py","timestamp":1692155331856},{"id":"UJ19.py","timestamp":1692155411406},{"id":"be5M.py","timestamp":1692155841741},{"id":"1gs5.py","source":"undoRedo.source","timestamp":1692155844109},{"id":"XKmo.py","timestamp":1692155846109},{"id":"hkGa.py","timestamp":1692155865873},{"id":"U23x.py","timestamp":1692155881172},{"id":"hXwM.py","source":"undoRedo.source","timestamp":1692155886144},{"id":"4GMb.py","timestamp":1692155901144},{"id":"7eaJ.py","timestamp":1692156068000},{"id":"08kr.py","timestamp":1692174429818},{"id":"ety4.py","timestamp":1692174458894},{"id":"Gm01.py","timestamp":1692174487535},{"id":"V32L.py","timestamp":1692175279398},{"id":"BwkZ.py","timestamp":1692175298490},{"id":"x1SP.py","timestamp":1692175319155},{"id":"1TaT.py","timestamp":1692175386023},{"id":"Wm9Y.py","timestamp":1692175398887},{"id":"vUIu.py","timestamp":1692175462308},{"id":"fxWJ.py","timestamp":1692175505976},{"id":"WQ3T.py","timestamp":1692175680314},{"id":"ZqhE.py","timestamp":1692175756039},{"id":"EQES.py","timestamp":1692176147822},{"id":"KR57.py","timestamp":1692176171527},{"id":"WC8q.py","timestamp":1692176285904},{"id":"YY9z.py","timestamp":1692176309836}]}